README.md
setup.py
pyeasex/__init__.py
pyeasex/api.py
pyeasex/ctypes.py
pyeasex/geojson.py
pyeasex/pipe.py
pyeasex/simulation.py
pyeasex.egg-info/PKG-INFO
pyeasex.egg-info/SOURCES.txt
pyeasex.egg-info/dependency_links.txt
pyeasex.egg-info/top_level.txt