Metadata-Version: 2.1
Name: pyeasex
Version: 0.0.12
Summary: pyeasex
Home-page: 
Author: ease-x
Author-email: admin@ease-x.com
Classifier: Programming Language :: Python :: 3
Classifier: License :: OSI Approved :: MIT License
Classifier: Operating System :: OS Independent
Requires-Python: >=3.6
